pdpbox/__init__.py
pdpbox/_version.py
pdpbox/get_example.py
pdpbox/info_plot_utils.py
pdpbox/info_plots.py
pdpbox/pdp.py
pdpbox/pdp_utils.py
pdpbox/styles.py
pdpbox/utils.py
pdpbox/examples/otto/otto_data.csv
pdpbox/examples/otto/otto_info.json
pdpbox/examples/otto/otto_model.pkl
pdpbox/examples/ross/ross_data.csv
pdpbox/examples/ross/ross_info.json
pdpbox/examples/ross/ross_model.pkl
pdpbox/examples/titanic/titanic_data.csv
pdpbox/examples/titanic/titanic_info.json
pdpbox/examples/titanic/titanic_model.pkl
PDPbox-0.3.0.dist-info/LICENSE.txt
PDPbox-0.3.0.dist-info/METADATA
PDPbox-0.3.0.dist-info/WHEEL
PDPbox-0.3.0.dist-info/top_level.txt
PDPbox-0.3.0.dist-info/RECORD
