Metadata-Version: 2.1
Name: PDPbox
Version: 0.3.0
Summary: Python partial dependence plot toolbox
Home-page: https://github.com/SauceCat/PDPbox
Author: sosuneko
Author-email: jiangchun.lee@gmail.com
License: MIT
License-File: LICENSE.txt
